astrodendro/__init__.py
astrodendro/analysis.py
astrodendro/dendrogram.py
astrodendro/flux.py
astrodendro/plot.py
astrodendro/progressbar.py
astrodendro/pruning.py
astrodendro/scatter.py
astrodendro/structure.py
astrodendro/structure_collection.py
astrodendro/version.py
astrodendro/viewer.py
astrodendro/io/__init__.py
astrodendro/io/fits.py
astrodendro/io/handler.py
astrodendro/io/hdf5.py
astrodendro/io/util.py
astrodendro/io/tests/__init__.py
astrodendro/io/tests/test_fits.py
astrodendro/io/tests/test_hdf5.py
astrodendro/io/tests/data/dendro.fits
astrodendro/io/tests/data/dendro.hdf5
astrodendro/io/tests/data/dendro_old.fits
astrodendro/io/tests/data/dendro_old.hdf5
astrodendro/tests/__init__.py
astrodendro/tests/_testdata.py
astrodendro/tests/benchmark.py
astrodendro/tests/build_benchmark.py
astrodendro/tests/sample-data-hl.npz
astrodendro/tests/test_analysis.py
astrodendro/tests/test_compute.py
astrodendro/tests/test_flux.py
astrodendro/tests/test_index.py
astrodendro/tests/test_io.py
astrodendro/tests/test_is_independent.py
astrodendro/tests/test_pruning.py
astrodendro/tests/test_recursion.py
astrodendro/tests/test_structure.py
astrodendro/tests/test_viewer.py
astrodendro/tests/benchmark_data/2d.fits
astrodendro/tests/benchmark_data/2d1.fits
astrodendro/tests/benchmark_data/2d2.fits
astrodendro/tests/benchmark_data/2d3.fits
astrodendro/tests/benchmark_data/3d.fits
astrodendro/tests/benchmark_data/3d1.fits
astrodendro/tests/benchmark_data/3d2.fits
astrodendro/tests/benchmark_data/3d3.fits
astrodendro-0.3.1.dist-info/LICENSE
astrodendro-0.3.1.dist-info/METADATA
astrodendro-0.3.1.dist-info/WHEEL
astrodendro-0.3.1.dist-info/top_level.txt
astrodendro-0.3.1.dist-info/RECORD
