Metadata-Version: 2.1
Name: astrodendro
Version: 0.3.1
Summary: Python package for computation of astronomical dendrograms
Author: Chris Beaumont, Adam Ginsburg, Braden MacDonald, and Erik Rosolowsky
Author-email: Thomas Robitaille <thomas.robitaille@gmail.com>
License: MIT
Project-URL: homepage, https://www.dendrograms.org/
Project-URL: documentation, https://dendrograms.readthedocs.io/en/stable/
Project-URL: repository, https://github.com/dendrograms/astrodendro
Classifier: Programming Language :: Python :: 3
Requires-Python: >=3.8
License-File: LICENSE
Requires-Dist: astropy >=5
Requires-Dist: h5py >=3
Requires-Dist: matplotlib >=3.3
Requires-Dist: numpy >=1.20
Provides-Extra: docs
Requires-Dist: aplpy ; extra == 'docs'
Requires-Dist: numpydoc ; extra == 'docs'
Requires-Dist: sphinx <7 ; extra == 'docs'
Requires-Dist: sphinx-astropy ; extra == 'docs'
Provides-Extra: test
Requires-Dist: pytest ; extra == 'test'
Requires-Dist: pytest-cov ; extra == 'test'
